{
    "success": true,
    "data": [
        {
            "key": "1",
            "resourceName": "XXX人口表",
            "downloadCount": "234次",
            "pumpFlow": "657m"
        },
        {
            "key": "2",
            "resourceName": "XXX人口表",
            "downloadCount": "234",
            "pumpFlow": "657"
        },
        {
            "key": "3",
            "resourceName": "XXX人口表",
            "downloadCount": "234",
            "pumpFlow": "657"
        },
        {
            "key": "4",
            "resourceName": "XXX人口表",
            "downloadCount": "234",
            "pumpFlow": "657"
        },
        {
            "key": "5",
            "resourceName": "XXX人口表",
            "downloadCount": "234",
            "pumpFlow": "657"
        },
        {
            "key": "6",
            "resourceName": "XXX人口表",
            "downloadCount": "234",
            "pumpFlow": "657"
        }
    ]
}